dploy_kickstart/__init__.py
dploy_kickstart/annotations.py
dploy_kickstart/cmd.py
dploy_kickstart/deps.py
dploy_kickstart/errors.py
dploy_kickstart/openapi.py
dploy_kickstart/server.py
dploy_kickstart/transformers.py
dploy_kickstart/wrapper.py
dploy_kickstart-0.1.9.dist-info/entry_points.txt
dploy_kickstart-0.1.9.dist-info/LICENSE
dploy_kickstart-0.1.9.dist-info/WHEEL
dploy_kickstart-0.1.9.dist-info/METADATA
dploy_kickstart-0.1.9.dist-info/RECORD
