Metadata-Version: 2.1
Name: dploy-kickstart
Version: 0.1.9
Summary: Expose your functions as HTTP endpoints.
Home-page: https://github.com/dploy-ai/dploy-kickstart/
License: MIT
Author: Bart Smeets
Author-email: bart@dploy.ai
Requires-Python: >=3.7,<4.0
Classifier: License :: OSI Approved :: MIT License
Classifier: Programming Language :: Python :: 3
Classifier: Programming Language :: Python :: 3.7
Classifier: Programming Language :: Python :: 3.8
Classifier: Programming Language :: Python :: 3.9
Requires-Dist: apispec (>=3.3.0,<4.0.0)
Requires-Dist: click (>=7.1.2,<8.0.0)
Requires-Dist: flask (>=1.1.2,<2.0.0)
Requires-Dist: paste (>=3.4.0,<4.0.0)
Requires-Dist: waitress (>=1.4.3,<2.0.0)
